odoo/addons/stock_account_operating_unit/README.rst
odoo/addons/stock_account_operating_unit/__init__.py
odoo/addons/stock_account_operating_unit/__manifest__.py
odoo/addons/stock_account_operating_unit/i18n/es.po
odoo/addons/stock_account_operating_unit/i18n/stock_account_operating_unit.pot
odoo/addons/stock_account_operating_unit/model/__init__.py
odoo/addons/stock_account_operating_unit/model/stock_move.py
odoo/addons/stock_account_operating_unit/readme/CONFIGURATION.rst
odoo/addons/stock_account_operating_unit/readme/CONTRIBUTORS.rst
odoo/addons/stock_account_operating_unit/readme/DESCRIPTION.rst
odoo/addons/stock_account_operating_unit/readme/USAGE.rst
odoo/addons/stock_account_operating_unit/static/description/icon.png
odoo/addons/stock_account_operating_unit/static/description/index.html
odoo/addons/stock_account_operating_unit/tests/__init__.py
odoo/addons/stock_account_operating_unit/tests/test_stock_account_operating_unit.py
odoo_addon_stock_account_operating_unit-15.0.1.0.0.7.dist-info/METADATA
odoo_addon_stock_account_operating_unit-15.0.1.0.0.7.dist-info/WHEEL
odoo_addon_stock_account_operating_unit-15.0.1.0.0.7.dist-info/top_level.txt
odoo_addon_stock_account_operating_unit-15.0.1.0.0.7.dist-info/RECORD
