Metadata-Version: 2.1
Name: odoo-addon-stock_account_operating_unit
Version: 15.0.1.0.0.7
Summary: Create journal entries in moves between internal locations with different operating units.
Home-page: https://github.com/OCA/operating-unit
Author: ForgeFlow, Serpent Consulting Services Pvt. Ltd.,Odoo Community Association (OCA)
Author-email: support@odoo-community.org
License: LGPL-3
Classifier: Programming Language :: Python
Classifier: Framework :: Odoo
Classifier: Framework :: Odoo :: 15.0
Classifier: License :: OSI Approved :: GNU Lesser General Public License v3 (LGPLv3)
Requires-Python: >=3.8
Requires-Dist: odoo-addon-account-operating-unit<15.1dev,>=15.0dev
Requires-Dist: odoo-addon-stock-operating-unit<15.1dev,>=15.0dev
Requires-Dist: odoo<15.1dev,>=15.0a
